{
   "format_version": "1.20.30",
   "minecraft:recipe_shaped": {
      "description": {
         "identifier": "mbl_ts:razor_wire_recipe"
      },
      "tags": [
         "crafting_table"
      ],
      "pattern": [
         "# #",
         " A ",
         "# #"
      ],
      "key": {
         "A": {
            "item": "mbl_ts:zinc_ingot"
         },
         "#": {
            "item": "minecraft:iron_nugget"
         }
      },
      "unlock": [
         {
            "item": "minecraft:iron_nugget"
         }
      ],
      "result": {
         "item": "mbl_ts:razor_wire",
         "count": 2
      }
   }
}