{
   "format_version":"1.8.0",
   "render_controllers":{
      "controller.render.zombie_small":{
         "arrays":{
            "textures":{
               "Array.variants":[
                  "Texture.default",
                  "Texture.zombie_2",
                  "Texture.zombie_3",
                  "Texture.zombie_4",
                  "Texture.zombie_5",
                  "Texture.zombie_6",
                  "Texture.zombie_7",
                  "Texture.zombie_8"
               ]
            }
         },
         "geometry":"Geometry.default",
         "materials":[
            {
               "*":"Material.default"
            }
         ],
         "textures":[
            "Array.variants[query.property('mbl_ts:skin')]"
         ],
         "is_hurt_color":{
            "r":"0.0",
            "g":"0.0",
            "b":"0.0",
            "a":"0.0"
         }
      }
   }
}